filecleaner/__init__.py
filecleaner/cache.py
filecleaner/main.py
filecleaner/media_tools.py
media_file_cleaner-0.3.1.dist-info/METADATA
media_file_cleaner-0.3.1.dist-info/WHEEL
media_file_cleaner-0.3.1.dist-info/entry_points.txt
media_file_cleaner-0.3.1.dist-info/top_level.txt
media_file_cleaner-0.3.1.dist-info/RECORD
