Metadata-Version: 2.1
Name: media-file-cleaner
Version: 0.3.1
Summary: Cleans a directory of media files.
Home-page: https://gitlab.com/oleksandr.zelentsov/media-file-cleaner
Author: Oleksandr Zelentsov
Author-email: oleksandrzelentsov@gmail.com
Requires-Python: >=3.10.4
Requires-Dist: ffmpy (==0.3.0)
